quool/__init__.py
quool/broker.py
quool/evaluator.py
quool/friction.py
quool/order.py
quool/scheduler.py
quool/source.py
quool/strategy.py
quool/util.py
quool/brokers/__init__.py
quool/brokers/ashare.py
quool/brokers/util.py
quool/brokers/xueqiu.py
quool/brokers/xuntou.py
quool/sources/__init__.py
quool/sources/dataframe.py
quool/sources/parquet.py
quool/sources/realtime.py
quool/sources/util.py
quool/sources/xuntou.py
quool-7.0.11.dist-info/licenses/LICENSE
test/test.py
test/util.py
test/migrates/mig.py
test/temp/gpt.py
test/temp/migrate.py
test/temp/ocr.py
test/temp/process.py
test/temp/sort_order.py
test/temp/test_trades.py
test/temp/text_tract.py
test/temp/transcribe.py
quool-7.0.11.dist-info/METADATA
quool-7.0.11.dist-info/WHEEL
quool-7.0.11.dist-info/top_level.txt
quool-7.0.11.dist-info/RECORD
