Metadata-Version: 2.4
Name: quool
Version: 7.0.11
Summary: Quantitative Toolkit - a helper in quant developing
Author-email: ppoak <ppoak@foxmail.com>
Project-URL: Homepage, https://github.com/ppoak/quool
Keywords: quant,framework,finance
Classifier: Programming Language :: Python :: 3
Classifier: License :: OSI Approved :: MIT License
Classifier: Operating System :: OS Independent
Requires-Python: >=3.10
License-File: LICENSE
Requires-Dist: numpy>=2.0
Requires-Dist: pandas>=2.0
Requires-Dist: joblib>=1.5.2
Requires-Dist: pyarrow>=21.0.0
Requires-Dist: requests>=2.32.5
Requires-Dist: markdown>=3.8.2
Requires-Dist: retry>=0.9.2
Requires-Dist: apscheduler>=3.11.0
Requires-Dist: duckdb>=1.0
Requires-Dist: tabulate>=0.9.0
Dynamic: license-file
